{
  "NameKey": "auth",
  "ValueKey": "bVvIy9jiIxcYadD2ubfwUnR5zLGGPubSYtLD55xeoxbykWtdEuiGy/DHwDGHDX7lq2C6hr7izGE=",
  "language": [],
  "title": "Enquête de Satisfaction concernant le service client",
  "subTitle": "Contribuez à l’amélioration de notre service",
  "pic": "Eudonet.svg_.png",
  "description": "Cher client, Dans le cadre de l'amélioration de nos produits et services, nous souhaiterions recueillir votre avis quant à la qualité de nos produits et services. Accordez-nous quelques minutes pour répondre à ce questionnaire",
  "footForm": "<span style=\"font-size:9pt\"><span style=\"font-family:verdana,geneva,sans-serif\">Copyright Eudonet.</span></span>",
  "confirmMsg": "<span style=\"font-size:9pt\"><span style=\"font-family:verdana,geneva,sans-serif\">Merci de votre participation</span></span>",
  "closureMsg": "L'enquete est finie. Merci.",
  "signature": "toute l’équipe d'Eudonet",
  "pages": [{
    "number": 1,
    "questions": [{
      "required": true,
      "type": "BIRTHDAY",
      "id": 80,
      "order": 1,
      "theme": "Votre appel",
      "question": "Date de votre appel",
      "toolTip": "indiquer la date",
      "response": {
        "idQuestion": 80,
        "value": "2018-08-03T00:00:00Z"
      },
      "lnkResponse": [],
      "lnkQuestion": null
    }, {
      "required": false,
      "watermark": null,
      "type": "NUM",
      "id": 88,
      "order": 2,
      "theme": "Votre appel",
      "question": "Combien de temps en minutes avez-vous passé avec le service client ?",
      "toolTip": null,
      "response": {
        "idQuestion": 88,
        "value": 3
      },
      "lnkResponse": [],
      "lnkQuestion": null
    }, {
      "required": false,
      "watermark": null,
      "responseChoices": [{
        "id": 3010068,
        "value": "Pas du tout satisfait"
      }, {
        "id": 3010067,
        "value": "Pas satisfait"
      }, {
        "id": 3010066,
        "value": "Satisfait"
      }, {
        "id": 3010065,
        "value": "Entièrement satisfait"
      }],
      "type": "SIMPLE",
      "id": 81,
      "order": 3,
      "theme": "Votre appel",
      "question": "Comment jugez-vous la qualité de votre appel",
      "toolTip": null,
      "response": {
        "idQuestion": 81,
        "value": [3010066]
      },
      "lnkResponse": [],
      "lnkQuestion": null
    }, {
      "required": false,
      "watermark": null,
      "type": "MEMO",
      "id": 91,
      "order": 4,
      "theme": "Votre appel",
      "question": "Precisez",
      "toolTip": "Merci de préciser votre réponse.",
      "response": {
        "idQuestion": 91,
        "value": "lkjkllkj"
      },
      "lnkResponse": [{
        "id": 3010068,
        "value": "Pas du tout satisfait"
      }, {
        "id": 3010067,
        "value": "Pas satisfait"
      }],
      "lnkQuestion": 81
    }, {
      "required": false,
      "watermark": null,
      "responseChoices": [{
        "id": 68,
        "value": "Social Network"
      }, {
        "id": 69,
        "value": "References"
      }, {
        "id": 70,
        "value": "Web"
      }, {
        "id": 3010060,
        "value": "Parce que j’avais besoin de plus d’informations sur le produit ou service"
      }, {
        "id": 3010061,
        "value": "En raison de problèmes avec le service"
      }, {
        "id": 3010062,
        "value": "Parce que je n’avais pas reçu le produit"
      }],
      "type": "MULTI",
      "id": 82,
      "order": 5,
      "theme": "Votre appel",
      "question": "Pour quelles raison avez-vous contacté le service client",
      "toolTip": "plusieurs réponse possible ",
      "response": null,
      "lnkResponse": [],
      "lnkQuestion": null
    }, {
      "required": false,
      "watermark": null,
      "responseChoices": [{
        "id": 76,
        "value": "Je ne sais pas"
      }, {
        "id": 3010068,
        "value": "Pas du tout satisfait"
      }, {
        "id": 3010067,
        "value": "Pas satisfait"
      }, {
        "id": 3010066,
        "value": "Satisfait"
      }, {
        "id": 3010065,
        "value": "Entièrement satisfait"
      }],
      "type": "LISTE",
      "id": 83,
      "order": 6,
      "theme": "Votre appel",
      "question": "evaluation de votre appel ",
      "toolTip": null,
      "response": {
        "idQuestion": 83,
        "value": 3010066
      },
      "lnkResponse": [],
      "lnkQuestion": null
    }, {
      "required": false,
      "watermark": null,
      "type": "MEMO",
      "id": 94,
      "order": 7,
      "theme": "Votre appel",
      "question": "Précisez",
      "toolTip": null,
      "response": {
        "idQuestion": 94,
        "value": "xvcvbnb,n;"
      },
      "lnkResponse": [{
        "id": 3010068,
        "value": "Pas du tout satisfait"
      }, {
        "id": 3010067,
        "value": "Pas satisfait"
      }],
      "lnkQuestion": 83
    }, {
      "min": 1,
      "max": 20,
      "Step": 0.5,
      "type": "RANGE",
      "id": 84,
      "order": 8,
      "theme": "Votre appel",
      "question": "Si vous deviez donner une note à votre interlocuteur",
      "toolTip": null,
      "response": {
        "idQuestion": 84,
        "value": 18
      },
      "lnkResponse": [],
      "lnkQuestion": null
    }]
  }, {
    "number": 2,
    "questions": [{
      "type": "TITLE",
      "id": 87,
      "order": 9,
      "theme": "Vos informations ",
      "question": "Ces informations stockées ne seront en aucun cas utilisées à des fins commerciales, ni transférées à des tiers. ",
      "toolTip": null,
      "response": null,
      "lnkResponse": [],
      "lnkQuestion": null
    }, {
      "required": false,
      "type": "BIRTHDAY",
      "id": 85,
      "order": 10,
      "theme": "Vos informations ",
      "question": "Veuillez indiquer votre date de naissance ",
      "toolTip": null,
      "response": {
        "idQuestion": 85,
        "value": "2018-08-03T00:00:00Z"
      },
      "lnkResponse": [],
      "lnkQuestion": null
    }, {
      "number": 5,
      "type": "STARS",
      "id": 86,
      "order": 11,
      "theme": "Vos informations ",
      "question": "votre niveau de compétence sur l'outils",
      "toolTip": null,
      "response": {
        "idQuestion": 86,
        "value": "4"
      },
      "lnkResponse": [],
      "lnkQuestion": null
    }, {
      "required": false,
      "watermark": null,
      "responseChoices": [{
        "id": 3010138,
        "value": "Oui"
      }, {
        "id": 3010139,
        "value": "Non"
      }],
      "type": "BOOL",
      "id": 89,
      "order": 12,
      "theme": "Vos informations ",
      "question": "avez vous des enfants",
      "toolTip": null,
      "response": {
        "idQuestion": 89,
        "value": []
      },
      "lnkResponse": [],
      "lnkQuestion": null
    }, {
      "required": false,
      "watermark": null,
      "type": "TEXT",
      "id": 90,
      "order": 13,
      "theme": "Vos informations ",
      "question": "En une phrase, comment décririez-vous vos connaissances sur l'outils",
      "toolTip": null,
      "response": {
        "idQuestion": 90,
        "value": "azazazrzaazr"
      },
      "lnkResponse": [],
      "lnkQuestion": null
    }, {
      "required": false,
      "watermark": null,
      "type": "CAPTURE",
      "id": 92,
      "order": 14,
      "theme": "Votre appel",
      "question": "Veuillez signer ",
      "toolTip": null,
      "response": null,
      "lnkResponse": [],
      "lnkQuestion": null
    }]
  }]
}
